skill_seekers/__init__.py
skill_seekers/py.typed
skill_seekers/cli/__init__.py
skill_seekers/cli/ai_enhancer.py
skill_seekers/cli/api_reference_builder.py
skill_seekers/cli/architectural_pattern_detector.py
skill_seekers/cli/code_analyzer.py
skill_seekers/cli/codebase_scraper.py
skill_seekers/cli/config_command.py
skill_seekers/cli/config_enhancer.py
skill_seekers/cli/config_extractor.py
skill_seekers/cli/config_manager.py
skill_seekers/cli/config_validator.py
skill_seekers/cli/conflict_detector.py
skill_seekers/cli/constants.py
skill_seekers/cli/dependency_analyzer.py
skill_seekers/cli/doc_scraper.py
skill_seekers/cli/enhance_skill.py
skill_seekers/cli/enhance_skill_local.py
skill_seekers/cli/enhance_status.py
skill_seekers/cli/estimate_pages.py
skill_seekers/cli/generate_router.py
skill_seekers/cli/github_fetcher.py
skill_seekers/cli/github_scraper.py
skill_seekers/cli/guide_enhancer.py
skill_seekers/cli/how_to_guide_builder.py
skill_seekers/cli/install_agent.py
skill_seekers/cli/install_skill.py
skill_seekers/cli/language_detector.py
skill_seekers/cli/llms_txt_detector.py
skill_seekers/cli/llms_txt_downloader.py
skill_seekers/cli/llms_txt_parser.py
skill_seekers/cli/main.py
skill_seekers/cli/markdown_cleaner.py
skill_seekers/cli/merge_sources.py
skill_seekers/cli/package_multi.py
skill_seekers/cli/package_skill.py
skill_seekers/cli/pattern_recognizer.py
skill_seekers/cli/pdf_extractor_poc.py
skill_seekers/cli/pdf_scraper.py
skill_seekers/cli/quality_checker.py
skill_seekers/cli/rate_limit_handler.py
skill_seekers/cli/resume_command.py
skill_seekers/cli/run_tests.py
skill_seekers/cli/setup_wizard.py
skill_seekers/cli/split_config.py
skill_seekers/cli/swift_patterns.py
skill_seekers/cli/test_example_extractor.py
skill_seekers/cli/test_unified_simple.py
skill_seekers/cli/unified_codebase_analyzer.py
skill_seekers/cli/unified_scraper.py
skill_seekers/cli/unified_skill_builder.py
skill_seekers/cli/upload_skill.py
skill_seekers/cli/utils.py
skill_seekers-2.7.4.dist-info/licenses/LICENSE
skill_seekers-2.7.4.dist-info/METADATA
skill_seekers-2.7.4.dist-info/WHEEL
skill_seekers-2.7.4.dist-info/entry_points.txt
skill_seekers-2.7.4.dist-info/top_level.txt
skill_seekers-2.7.4.dist-info/RECORD
