Metadata-Version: 2.4
Name: skill-seekers
Version: 2.7.4
Summary: Convert documentation websites, GitHub repositories, and PDFs into Claude AI skills. International support with Chinese (简体中文) documentation.
Author: Yusuf Karaaslan
License: MIT
Project-URL: Homepage, https://skillseekersweb.com/
Project-URL: Website, https://skillseekersweb.com/
Project-URL: Repository, https://github.com/yusufkaraaslan/Skill_Seekers
Project-URL: Bug Tracker, https://github.com/yusufkaraaslan/Skill_Seekers/issues
Project-URL: Documentation, https://skillseekersweb.com/
Project-URL: Config Browser, https://skillseekersweb.com/
Project-URL: 中文文档 (Chinese), https://github.com/yusufkaraaslan/Skill_Seekers/blob/main/README.zh-CN.md
Keywords: claude,ai,documentation,scraping,skills,llm,mcp,automation,i18n,chinese,international
Classifier: Development Status :: 4 - Beta
Classifier: Intended Audience :: Developers
Classifier: License :: OSI Approved :: MIT License
Classifier: Operating System :: OS Independent
Classifier: Programming Language :: Python :: 3
Classifier: Programming Language :: Python :: 3.10
Classifier: Programming Language :: Python :: 3.11
Classifier: Programming Language :: Python :: 3.12
Classifier: Programming Language :: Python :: 3.13
Classifier: Topic :: Software Development :: Documentation
Classifier: Topic :: Software Development :: Libraries :: Python Modules
Classifier: Topic :: Text Processing :: Markup :: Markdown
Classifier: Natural Language :: English
Classifier: Natural Language :: Chinese (Simplified)
Requires-Python: >=3.10
License-File: LICENSE
Requires-Dist: requests>=2.32.5
Requires-Dist: beautifulsoup4>=4.14.2
Requires-Dist: PyGithub>=2.5.0
Requires-Dist: GitPython>=3.1.40
Requires-Dist: httpx>=0.28.1
Requires-Dist: anthropic>=0.76.0
Requires-Dist: PyMuPDF>=1.24.14
Requires-Dist: Pillow>=11.0.0
Requires-Dist: pytesseract>=0.3.13
Requires-Dist: pydantic>=2.12.3
Requires-Dist: pydantic-settings>=2.11.0
Requires-Dist: python-dotenv>=1.1.1
Requires-Dist: jsonschema>=4.25.1
Requires-Dist: click>=8.3.0
Requires-Dist: Pygments>=2.19.2
Requires-Dist: pathspec>=0.12.1
Requires-Dist: networkx>=3.0
Provides-Extra: mcp
Requires-Dist: mcp<2,>=1.25; extra == "mcp"
Requires-Dist: httpx>=0.28.1; extra == "mcp"
Requires-Dist: httpx-sse>=0.4.3; extra == "mcp"
Requires-Dist: uvicorn>=0.38.0; extra == "mcp"
Requires-Dist: starlette>=0.48.0; extra == "mcp"
Requires-Dist: sse-starlette>=3.0.2; extra == "mcp"
Provides-Extra: gemini
Requires-Dist: google-generativeai>=0.8.0; extra == "gemini"
Provides-Extra: openai
Requires-Dist: openai>=1.0.0; extra == "openai"
Provides-Extra: all-llms
Requires-Dist: google-generativeai>=0.8.0; extra == "all-llms"
Requires-Dist: openai>=1.0.0; extra == "all-llms"
Provides-Extra: all
Requires-Dist: mcp<2,>=1.25; extra == "all"
Requires-Dist: httpx>=0.28.1; extra == "all"
Requires-Dist: httpx-sse>=0.4.3; extra == "all"
Requires-Dist: uvicorn>=0.38.0; extra == "all"
Requires-Dist: starlette>=0.48.0; extra == "all"
Requires-Dist: sse-starlette>=3.0.2; extra == "all"
Requires-Dist: google-generativeai>=0.8.0; extra == "all"
Requires-Dist: openai>=1.0.0; extra == "all"
Dynamic: license-file
